{
  "reikai": {
    "entries": {
      "0000": [
        {
          "def": "あるものごとが、ほかのものごとに<ruby><rb>力</rb><rt>ちから</rt></ruby>をおよぼして、そのようすを<ruby><rb>変</rb><rt>か</rt></ruby>えること。",
          "hyouki": [
            "影響"
          ]
        }
      ],
      "0001": [
        {
          "def": "<ruby><rb>競技</rb><rt>きょうぎ</rt></ruby>に<ruby><rb>出</rb><rt>で</rt></ruby>るために<ruby><rb>選</rb><rt>えら</rt></ruby>ばれた<ruby><rb>人</rb><rt>ひと</rt></ruby>。",
          "hyouki": [
            "選手"
          ]
        }
      ],
      "0002": [
        {
          "def": "<ruby><rb>多</rb><rt>おお</rt></ruby>くの<ruby><rb>人</rb><rt>ひと</rt></ruby>が<ruby><rb>集</rb><rt>あつ</rt></ruby>まる<ruby><rb>会</rb><rt>かい</rt></ruby>。",
          "hyouki": [
            "大会"
          ]
        },
        {
          "def": "ある<ruby><rb>組織</rb><rt>そしき</rt></ruby>の<ruby><rb>全員</rb><rt>ぜんいん</rt></ruby>が<ruby><rb>集</rb><rt>あつ</rt></ruby>まる<ruby><rb>会</rb><rt>かい</rt></ruby>。",
          "hyouki": [
            "大会"
          ]
        }
      ],
      "0003": [
        {
          "def": "<ruby><rb>競技</rb><rt>きょうぎ</rt></ruby>などで、<ruby><rb>一位</rb><rt>いちい</rt></ruby>で<ruby><rb>勝</rb><rt>か</rt></ruby>つこと。",
          "hyouki": [
            "優勝"
          ]
        }
      ],
      "0004": [
        {
          "def": "まじめで、まごころがこもっていること。",
          "hyouki": [
            "誠実"
          ]
        }
      ],
      "0005": [
        {
          "def": "すなおで、ひかえめなようす。つつましいようす。",
          "hyouki": [
            "謙虚"
          ]
        }
      ],
      "0006": [
        {
          "def": "<ruby><rb>共和国</rb><rt>きょうわこく</rt></ruby>で、その<ruby><rb>国</rb><rt>くに</rt></ruby>を<ruby><rb>代表</rb><rt>だいひょう</rt></ruby>する<ruby><rb>人</rb><rt>ひと</rt></ruby>。",
          "hyouki": [
            "大統領"
          ]
        }
      ]
    }
  }
}
