{
  "cate": "5",
  "date": "4æ24æ¥ 16æ40å",
  "datetime": "2019-04-24T16:40",
  "video": "/news/html/20190424/movie/k10011894851_201904241728_201904241730.html",
  "duration": 184,
  "img": "html/20190424/K10011894851_1904241638_1904241640_01_02.jpg",
  "title": "スマホアプリで配車 中国「滴滴」が13都道府県にサービス拡大",
  "summary": "スマートフォンのアプリを使ってタクシーを呼ぶ配車サービスで、去年、日本に進出した中国の「滴滴」が、東京や京都など全国13の都道府県にサービスを拡大する方針を明らかにしました。",
  "more": "",
  "body": [
    {
      "title": "",
      "img": "html/20190424/K10011894851_1904241638_1904241640_01_03.jpg",
      "align": "",
      "text": "滴滴は去年、ソフトバンクと合弁会社を設立して大阪で配車サービスを始めていて、24日、記者会見を開いて今後の事業計画を発表しました。<br /><br />それによりますと、24日から東京と京都で新たにサービスを始めたほか、今年度中に北海道、兵庫、福岡などにも進出し、サービスエリアを13の都道府県に拡大するとしています。<br /><br />このサービスは、タクシーを利用したい人がスマホのアプリに出発地と目的地を入力すると、近くにいるタクシーを呼び出せる仕組みです。<br /><br />乗客とタクシーのマッチングにはＡＩ＝人工知能が活用されていて、乗客が待ち時間を短縮できるだけでなく、タクシー側も空車時間を減らせるメリットがあるとしています。<br /><br />中国最大手の滴滴は、去年から世界進出を加速させていて、利用者は５億人を超えているということです。<br /><br />合弁会社、ＤｉＤｉモビリティジャパンの菅野圭吾副社長は「大阪で磨いてきたものを東京やほかの都市に拡大する準備ができた。まだまだ知られていないサービスなので、便利さを追求してどんどん広げていきたい」と述べました。",
      "textPos": "bottom"
    },
    {
      "title": "アプリ使った配車サービス参入相次ぐ",
      "img": "html/20190424/K10011894851_1904241638_1904241640_01_04.jpg",
      "align": "",
      "text": "スマートフォンのアプリを使った配車サービスは、アメリカのウーバーが先駆けで、世界的には一般の車に客を乗せるライドシェアの形で普及しています。<br /><br />一方、日本では、ライドシェアは法律で禁じられているため、ウーバーもタクシーを配車するサービスを行っています。<br /><br />これに対してタクシー会社900社、７万台の車両が登録されているＪａｐａｎＴａｘｉが全国でサービスを行っているほか、ＩＴ企業のディー・エヌ・エーも去年から東京と神奈川でサービスを手がけています。<br /><br />さらに今月16日には、ソニーも東京でサービスを始め、競争が激しくなっています。<br /><br />滴滴は、アプリにクレジットカードを登録してキャッシュレスで決済すれば、タクシーを呼び出す際の「迎車料金」を無料にするキャンペーンを東京で実施するとしていて、各社が料金や使いやすさでどれだけ特色を出せるかが、利用を増やす鍵になりそうです。",
      "textPos": "bottom"
    }
  ],
  "relationNews": [
    {
      "link": "html/20190423/k10011893651000.html",
      "title": "携帯３社 メッセージアプリに追加サービス ＬＩＮＥに対抗",
      "date": "4月23日  18時40分",
      "datetime": "2019-04-23T18:40",
      "imgPath": "html/20190423/K10011893651_1904231815_1904231840_01_02.jpg",
      "iconPath": "html/20190423/K10011893651_1904231815_1904231840_02_01.jpg",
      "video": "",
      "duration": 0
    },
    {
      "link": "html/20190423/k10011892971000.html",
      "title": "サムスン 折り畳みスマホ “不具合”報道で発売延期",
      "date": "4月23日  7時45分",
      "datetime": "2019-04-23T07:45",
      "imgPath": "html/20190423/K10011892971_1904231124_1904231126_01_03.jpg",
      "iconPath": "html/20190423/K10011892971_1904231124_1904231126_02_01.jpg",
      "video": "https://www3.nhk.or.jp/news/html/20190423/movie/k10011892971_201904231124_201904231125.html",
      "duration": 66
    },
    {
      "link": "html/20190423/k10011892621000.html",
      "title": "「共通アプリでＱＲコード決済」金融機関が今秋開始へ",
      "date": "4月23日  4時22分",
      "datetime": "2019-04-23T04:22",
      "imgPath": "html/20190423/K10011892621_1904222226_1904230422_01_02.jpg",
      "iconPath": "html/20190423/K10011892621_1904222226_1904230422_02_01.jpg",
      "video": "https://www3.nhk.or.jp/news/html/20190423/movie/k10011892621_201904230524_201904230533.html",
      "duration": 53
    },
    {
      "link": "html/20190422/k10011892161000.html",
      "title": "中国スマート家電急拡大 日本のあの商品も！？",
      "date": "4月22日  15時51分",
      "datetime": "2019-04-22T15:51",
      "imgPath": "html/20190422/K10011892161_1904221516_1904221517_01_02.jpg",
      "iconPath": "html/20190422/K10011892161_1904221516_1904221517_02_01.jpg",
      "video": "",
      "duration": 0
    }
  ],
  "relationLink": [
    {
      "link": "http://www3.nhk.or.jp/news/html/20190111/k10011774891000.html",
      "title": "中国の巨人「滴滴」に潜入した",
      "time": "ビジネス特集 1月11日",
      "datetime": "2019-01-11"
    },
    {
      "link": "http://www3.nhk.or.jp/news/html/20190109/k10011772081000.html",
      "title": "スマホ決済は地方を救う？",
      "time": "ビジネス特集 1月9日",
      "datetime": "2019-01-09"
    },
    {
      "link": "http://www3.nhk.or.jp/news/html/20190423/k10011893821000.html",
      "title": "お釣りが出せない!?",
      "time": "News Up 4月23日",
      "datetime": "2019-04-23"
    },
    {
      "link": "http://www3.nhk.or.jp/news/html/20190419/k10011889021000.html",
      "title": "“日本に戻らなければよかった”",
      "time": "News Up 4月19日",
      "datetime": "2019-04-19"
    }
  ],
  "word": [
    {
      "link": "word/0000009.html",
      "title": "IT・ネット"
    }
  ],
  "news_id": "k10011894851000",
  "yyyy": "2019",
  "mm": "04",
  "dd": "24",
  "url": "https://www3.nhk.or.jp/news/html/20190424/k10011894851000.html?utm_int=nsearch_contents_search-items_001"
}