{
  "cate": "1",
  "date": "4æ9æ¥ 16æ33å",
  "datetime": "2019-04-09T16:33",
  "video": "",
  "duration": 0,
  "img": "html/20190409/K10011878201_1904091637_1904091643_01_02.jpg",
  "title": "ゴーン前会長「すべての嫌疑で私は無実 陰謀だ」動画を公開",
  "summary": "日産自動車のゴーン前会長が、再逮捕される前にみずからの主張を英語で録画した動画を９日、弁護士が公開し、この中で前会長は「すべての嫌疑について私は無実で、今起きていることは陰謀だ」と訴えました。",
  "more": "",
  "body": [
    {
      "title": "",
      "img": "html/20190409/K10011878201_1904091637_1904091643_01_03.jpg",
      "align": "",
      "text": "日産自動車の前会長カルロス・ゴーン容疑者（65）はオマーンの販売代理店に日産から支出させた資金の一部を私的に流用したとして、今月４日、特別背任の疑いで東京地検特捜部に再逮捕されました。<br /><br />前会長の弁護を担当する弘中惇一郎弁護士は９日、東京 丸の内の日本外国特派員協会で会見を開き、前会長が再逮捕される前にみずからの主張を事前に英語で録画した、およそ７分30秒の動画を公開しました。<br /><br />この中で、前会長はまず「すべての嫌疑について私は無実で、私に対しての非難も事実無根だ。こうした非難は私を強欲な人物、あるいは独裁的な人物として塗り固めるためになされたもので、今起きていることは『陰謀』『謀略』『中傷』だ」と述べました。<br /><br />そして事件の背景については「アライアンスの次のステップ、つまり統合・合併に向けて進むことが、ある人たちには確かな脅威を与え、日産の独立性を脅かすかもしれないと恐れた」としたうえで、「独立性は業績に支えられなければならず、独立性を得ること自体が目的となることはありえない。数名の幹部は明らかに自分たちの利益のために、自分勝手な恐れを抱いたために会社の価値を毀損した」と述べました。<br /><br />また今後の日産については「株価の下落と業績の低下を目にしながらも、現経営幹部には日産の業績向上やアライアンスの将来をより強化するためのビジョンはない。それを見るのは非常に悲しいことで、本当にうんざりさせられている。テーブルを囲んでコンセンサスで意思決定をしていくことは、競争の激しい自動車業界で何のビジョンも生み出さない」と述べ、現経営陣を強く批判しました。<br /><br />そして最後に、ゴーン前会長は「私が最も強く望むことは公正な裁判を受けることだが、弁護士から裁判の公正性について安心材料は提供してもらえていない。この裁判で私の無実を証明したいと、せつに願っている」と述べました。<br /><br />弘中弁護士によりますと、動画には当初、ゴーン前会長が批判した日産の経営陣の実名も記録されていましたが、弁護団の判断でその部分をカットし、前会長の了承も得たうえで公開したということです。<br /><br />弘中弁護士は前会長が事件の詳しい内容を説明しなかった理由について、「検察から証拠の開示や主張がほとんどされてない中で、前会長が想像で発言するのは不適当なためだ」と述べました。",
      "textPos": "bottom"
    },
    {
      "title": "弘中弁護士「黙秘するようアドバイス」",
      "img": "",
      "align": "",
      "text": "弘中弁護士は９日の記者会見の中で、「今回の逮捕・勾留は逃亡や証拠隠滅の防止ではなく、ゴーン前会長に不当な圧力をかけ、屈服させることをねらったものだ」と述べ、裁判所が勾留を認めたことを不服とし、10日、最高裁判所に特別抗告の手続きを取ることを明らかにしました。<br /><br />また、弁護団としてゴーン前会長に対し、取り調べでは黙秘するようアドバイスしていることも明らかにしました。<br /><br />このほか、東京地検特捜部が裁判所に参考人として尋問する手続きを請求したあとフランスに出国した妻のキャロルさんについて、「逮捕されることはないと確信し、証人として尋問に応じるようアドバイスした。キャロルさんは恐れておらず、尋問に応じる予定だ」と述べました。",
      "textPos": ""
    },
    {
      "title": "西川社長「一生懸命やっている」",
      "img": "",
      "align": "",
      "text": "日産自動車の西川廣人社長は９日夜、記者団に対して、ゴーン前会長が公開した動画の中で、今起きていることは日産の幹部による陰謀だなどと訴えたことについて「私は動画をじっくり見ていないので分からない」と述べました。<br /><br />また、前会長が、経営陣がビジョンを持っていないため、日産の業績が低迷していると批判したことについては「一生懸命やっていますので、そういうことはない」と述べました。<br /><br />一方、今週、フランスで開かれる日産、三菱自動車、ルノーの３社の経営トップでつくる新たな会議の初会合に向けては、「最初の会議なので、今ある問題点とこれから取り組むべきことを整理して、いくつかの活動をキックオフさせたい」と述べました。",
      "textPos": ""
    }
  ],
  "relationNews": [
    {
      "link": "html/20190409/k10011878151000.html",
      "title": "ゴーン前会長の動画公開 メッセージ全文",
      "date": "4月9日  16時03分",
      "datetime": "2019-04-09T16:03",
      "imgPath": "html/20190409/K10011878151_1904091559_1904091609_01_02.jpg",
      "iconPath": "html/20190409/K10011878151_1904091559_1904091609_02_01.jpg",
      "video": "",
      "duration": 0
    },
    {
      "link": "html/20190409/k10011878091000.html",
      "title": "ゴーン前会長の動画公開「すべての嫌疑で私は無実」",
      "date": "4月9日  15時28分",
      "datetime": "2019-04-09T15:28",
      "imgPath": "html/20190409/K10011878091_1904091522_1904091524_01_03.jpg",
      "iconPath": "html/20190409/K10011878091_1904091538_1904091542_02_01.jpg",
      "video": "",
      "duration": 0
    },
    {
      "link": "html/20190409/k10011877771000.html",
      "title": "ゴーン前会長の妻 仏ラジオの取材に「人権問題訴えるため」",
      "date": "4月9日  11時09分",
      "datetime": "2019-04-09T11:09",
      "imgPath": "html/20190409/K10011877771_1904090859_1904090904_01_02.jpg",
      "iconPath": "html/20190409/K10011877771_1904090859_1904090904_02_01.jpg",
      "video": "",
      "duration": 0
    },
    {
      "link": "html/20190409/k10011877631000.html",
      "title": "日産 新しい経営体制づくり本格化へ",
      "date": "4月9日  4時07分",
      "datetime": "2019-04-09T04:07",
      "imgPath": "html/20190409/K10011877631_1904090514_1904090520_01_03.jpg",
      "iconPath": "html/20190409/K10011877631_1904090514_1904090520_02_01.jpg",
      "video": "https://www3.nhk.or.jp/news/html/20190409/movie/k10011877631_201904090514_201904090519.html",
      "duration": 94
    }
  ],
  "relationLink": [
    {
      "link": "https://www3.nhk.or.jp/news/special/nissan_ghosn/",
      "title": "衝撃 日産ゴーン前会長 事件の行方",
      "time": "スペシャルコンテンツ",
      "datetime": ""
    },
    {
      "link": "https://www3.nhk.or.jp/news/special/heisei/interview/interview_02.html",
      "title": "森永卓郎さん「とてつもない大転落」",
      "time": "平成-次代への道標-",
      "datetime": ""
    },
    {
      "link": "https://www3.nhk.or.jp/news/special/heisei/interview/interview_05.html",
      "title": "尾木直樹さん「なんていう不幸せな時代」",
      "time": "平成-次代の道標-",
      "datetime": ""
    }
  ],
  "word": [
    {
      "link": "word/0000736.html",
      "title": "ゴーン前会長"
    },
    {
      "link": "word/0000737.html",
      "title": "ゴーン前会長 トップ"
    }
  ],
  "news_id": "k10011878201000",
  "yyyy": "2019",
  "mm": "04",
  "dd": "09",
  "url": "https://www3.nhk.or.jp/news/html/20190409/k10011878201000.html"
}