{
  "news_id": "k10011875651000",
  "news_prearranged_time": "2019-04-09 11:30:00",
  "title": "トルコの新しい空港　１年に２億人が利用できるようにする",
  "title_with_ruby": "トルコの<ruby>新<rt>あたら</rt></ruby>しい<ruby>空港<rt>くうこう</rt></ruby>　１<ruby>年<rt>ねん</rt></ruby>に２<ruby>億<rt>おく</rt></ruby><ruby>人<rt>にん</rt></ruby>が<ruby>利用<rt>りよう</rt></ruby>できるようにする",
  "outline_with_ruby": "<p>トルコでは<ruby>去年<rt>きょねん</rt></ruby>、「イスタンブール<ruby>空港<rt>くうこう</rt></ruby>」という<ruby>新<rt>あたら</rt></ruby>しい<ruby>空港<rt>くうこう</rt></ruby>が<a href='javascript:void(0)' class='dicWin' id='id-0000'>オープン</a>しました。",
  "has_news_web_image": true,
  "has_news_web_movie": true,
  "has_news_easy_image": false,
  "has_news_easy_movie": false,
  "has_news_easy_voice": true,
  "news_web_image_uri": "https://www3.nhk.or.jp/news/html/20190407/../20190407/K10011875651_1904070617_1904070620_01_03.jpg",
  "news_web_movie_uri": "k10011875651_201904070617_201904070619.mp4",
  "news_easy_image_uri": "''",
  "news_easy_movie_uri": "''",
  "news_easy_voice_uri": "k10011875651000.mp4",
  "url": "http://www3.nhk.or.jp/news/easy/k10011875651000/k10011875651000.html"
}